pyvisa_sim/__init__.py
pyvisa_sim/channels.py
pyvisa_sim/common.py
pyvisa_sim/component.py
pyvisa_sim/default.yaml
pyvisa_sim/devices.py
pyvisa_sim/highlevel.py
pyvisa_sim/parser.py
pyvisa_sim/version.py
pyvisa_sim/sessions/__init__.py
pyvisa_sim/sessions/gpib.py
pyvisa_sim/sessions/serial.py
pyvisa_sim/sessions/session.py
pyvisa_sim/sessions/tcpip.py
pyvisa_sim/sessions/usb.py
pyvisa_sim/testsuite/__init__.py
pyvisa_sim/testsuite/conftest.py
pyvisa_sim/testsuite/test_all.py
pyvisa_sim/testsuite/test_channel.py
pyvisa_sim/testsuite/test_common.py
pyvisa_sim/testsuite/test_parser.py
pyvisa_sim/testsuite/test_serial.py
pyvisa_sim/testsuite/fixtures/__init__.py
pyvisa_sim/testsuite/fixtures/channels.yaml
pyvisa_sim-0.7.1.dist-info/licenses/AUTHORS.rst
pyvisa_sim-0.7.1.dist-info/licenses/LICENSE.txt
pyvisa_sim-0.7.1.dist-info/METADATA
pyvisa_sim-0.7.1.dist-info/WHEEL
pyvisa_sim-0.7.1.dist-info/top_level.txt
pyvisa_sim-0.7.1.dist-info/RECORD
