Metadata-Version: 2.4
Name: PyVISA-sim
Version: 0.7.1
Summary: Simulated backend for PyVISA implementing TCPIP, GPIB, RS232, and USB resources
Author-email: "Hernan E. Grecco" <hernan.grecco@gmail.com>
Maintainer-email: "Matthieu C. Dartiailh" <m.dartiailh@gmail.com>
License: The MIT License
Project-URL: homepage, https://github.com/pyvisa/pyvisa-sim
Project-URL: documentation, https://pyvisa-sim.readthedocs.io/en/latest/
Project-URL: repository, https://github.com/pyvisa/pyvisa-sim
Project-URL: changelog, https://github.com/pyvisa/pyvisa-sim/blob/main/CHANGES.rst
Keywords: VISA,GPIB,USB,serial,RS232,measurement,acquisition,simulator,mock
Classifier: Development Status :: 4 - Beta
Classifier: Intended Audience :: Developers
Classifier: Intended Audience :: Science/Research
Classifier: License :: OSI Approved :: MIT License
Classifier: Operating System :: Microsoft :: Windows
Classifier: Operating System :: POSIX :: Linux
Classifier: Operating System :: MacOS :: MacOS X
Classifier: Programming Language :: Python
Classifier: Topic :: Scientific/Engineering :: Interface Engine/Protocol Translator
Classifier: Topic :: Software Development :: Libraries :: Python Modules
Classifier: Programming Language :: Python :: 3.10
Classifier: Programming Language :: Python :: 3.11
Classifier: Programming Language :: Python :: 3.12
Classifier: Programming Language :: Python :: 3.13
Requires-Python: >=3.10
License-File: LICENSE.txt
License-File: AUTHORS.rst
Requires-Dist: pyvisa>=1.15.0
Requires-Dist: PyYAML
Requires-Dist: stringparser
Requires-Dist: typing-extensions
Dynamic: license-file
